hypertion/__init__.py
hypertion/function_calling/__init__.py
hypertion/function_calling/compose.py
hypertion/function_calling/schema.py
hypertion/function_calling/utils.py
LICENSE
hypertion-2.0.0.dist-info/LICENSE
hypertion-2.0.0.dist-info/METADATA
hypertion-2.0.0.dist-info/WHEEL
hypertion-2.0.0.dist-info/RECORD
