Metadata-Version: 2.1
Name: hypertion
Version: 2.0.0
Summary: Streamlined and Efficient LLM function calling.
Home-page: https://github.com/synacktraa/hypertion
License: GPL-3.0-only
Keywords: function-calling,functionary,gorilla,mistral,claude,gpt
Author: Harsh Verma
Author-email: synacktra.work@gmail.com
Requires-Python: >=3.8,<4.0
Classifier: License :: OSI Approved :: GNU General Public License v3 (GPLv3)
Classifier: Programming Language :: Python :: 3
Classifier: Programming Language :: Python :: 3.8
Classifier: Programming Language :: Python :: 3.9
Classifier: Programming Language :: Python :: 3.10
Classifier: Programming Language :: Python :: 3.11
Classifier: Programming Language :: Python :: 3.12
Requires-Dist: docstring-parser (>=0.16,<0.17)
Requires-Dist: pydantic (>=1.10)
Project-URL: Repository, https://github.com/synacktraa/hypertion
